{
    "items": [
        {
            "id": 2,
            "name": "филиал 2",
            "area": [
                {
                    "x": 51.780261808802,
                    "y": 55.113123869611
                },
                {
                    "x": 51.780507655458,
                    "y": 55.172629250113
                },
                {
                    "x": 51.770065464915,
                    "y": 55.167000786196
                },
                {
                    "x": 51.762692230856,
                    "y": 55.123254412184
                },
                {
                    "x": 51.780261808802,
                    "y": 55.113123869611
                }
            ],
            "price": null,
            "filial": {
                "id": 1,
                "name": "filial 1",
                "city": "city",
                "address": "address",
                "minOrderCost": 123
            }
        }
    ],
    "meta": null
}
